{"legislative_session": "2025-2028", "identifier": "RCS0073", "title": "\u201cPara ordenar al Departamento de Transportaci\u00f3n y Obras P\u00fablicas, la Autoridad de los Puertos y a la Autoridad de Carreteras y Transportaci\u00f3n a rendir un informe sobre el estado de las rotulaciones, marcadores y luminarias en las carreteras alrededor de la Base Ramey y ordenarles a presentar a la Asamblea Legislativa un plan de trabajo detallado, a corto y mediano plazo, para atender las deficiencias y necesidades identificadas que incluya los posibles planes de desarrollo de infraestructura; y para otros asuntos relacionados.\u201d", "from_organization": "~{\"classification\": \"upper\"}", "classification": ["resolution"], "subject": [], "abstracts": [], "other_titles": [], "other_identifiers": [], "actions": [{"description": "Radicado", "date": "2025-06-11T04:00:00+00:00", "organization_id": "~{\"classification\": \"legislature\"}", "classification": ["introduction"], "related_entities": []}, {"description": "Aparece en Primera Lectura del Senado", "date": "2025-06-12T04:00:00+00:00", "organization_id": "~{\"classification\": \"upper\"}", "classification": ["reading-1"], "related_entities": []}, {"description": "Referido a Comisi\u00f3n(es)", "date": "2025-06-12T04:00:00+00:00", "organization_id": "~{\"classification\": \"legislature\"}", "classification": ["referral-committee"], "related_entities": []}], "sponsorships": [{"name": "Karen M. Rom\u00e1n Rodr\u00edguez - Sistema \u00danico de Tr\u00e1mite Legislativo", "classification": "primary", "entity_type": "person", "primary": true, "person_id": "~{\"name\": \"Karen M. Rom\\u00e1n Rodr\\u00edguez - Sistema \\u00danico de Tr\\u00e1mite Legislativo\"}", "organization_id": null}], "related_bills": [], "versions": [], "documents": [], "citations": [], "sources": [{"url": "https://sutra.oslpr.org/medidas/156460", "note": ""}], "extras": {}, "jurisdiction": {"id": "ocd-jurisdiction/country:us/territory:pr/government", "name": "Puerto Rico", "classification": "state", "division_id": "ocd-division/country:us/territory:pr"}, "scraped_at": "2025-07-28T17:21:13+00:00", "_id": "42a8d4a6-6bd7-11f0-ac25-fa5369b67b11"}