{
  "legislative_session": "2025-2028",
  "identifier": "PC0949",
  "title": "Para enmendar los Art\u00edculos 10, 23, 148, 149, 235 y 240 de la Ley N\u00fam. 210-2015, seg\u00fan enmendada, conocida como la \u201cLey del Registro de la Propiedad Inmobiliaria del Estado Libre Asociado de Puerto Rico\u201d, con el prop\u00f3sito de mejorar la precisi\u00f3n y confiabilidad de las descripciones inmobiliarias; y para otros fines relacionados.",
  "from_organization": "~{\"classification\": \"upper\"}",
  "classification": [
    "bill"
  ],
  "subject": [],
  "abstracts": [],
  "other_titles": [],
  "other_identifiers": [],
  "actions": [
    {
      "description": "Radicado",
      "date": "2025-10-27T04:00:00+00:00",
      "organization_id": "~{\"classification\": \"legislature\"}",
      "classification": [
        "introduction"
      ],
      "related_entities": [],
      "_processing": {
        "log_file_created": "2025-10-28T03:49:10Z"
      }
    }
  ],
  "sponsorships": [
    {
      "name": "Joel   Franqui Atiles - Sistema \u00danico de Tr\u00e1mite Legislativo",
      "classification": "primary",
      "entity_type": "person",
      "primary": true,
      "person_id": "~{\"name\": \"Joel   Franqui Atiles - Sistema \\u00danico de Tr\\u00e1mite Legislativo\"}",
      "organization_id": null
    }
  ],
  "related_bills": [],
  "versions": [],
  "documents": [],
  "citations": [],
  "sources": [
    {
      "url": "https://sutra.oslpr.org/medidas/159267",
      "note": ""
    }
  ],
  "extras": {},
  "jurisdiction": {
    "id": "ocd-jurisdiction/country:us/territory:pr/government",
    "name": "Puerto Rico",
    "classification": "state",
    "division_id": "ocd-division/country:us/territory:pr"
  },
  "_processing": {
    "logs_latest_update": "2025-10-28T03:49:10Z"
  }
}